vectorflow_client/__init__.py
vectorflow_client/chunk_enhancer.py
vectorflow_client/chunk_strategy.py
vectorflow_client/embeddings.py
vectorflow_client/embeddings_type.py
vectorflow_client/job.py
vectorflow_client/response.py
vectorflow_client/vector_db.py
vectorflow_client/vector_db_type.py
vectorflow_client/vectorflow.py
vectorflow_client-0.0.11.dist-info/METADATA
vectorflow_client-0.0.11.dist-info/WHEEL
vectorflow_client-0.0.11.dist-info/RECORD
