Metadata-Version: 2.1
Name: vectorflow_client
Version: 0.0.11
Summary: Use this Python client to embed documents with VectorFlow, an open source, high throughput, production ready vector embedding pipeline.
Project-URL: Client Homepage, https://github.com/dgarnitz/vectorflow/tree/main/client
Project-URL: VectorFlow Homepage, https://github.com/dgarnitz/vectorflow
Project-URL: Issues & Bugs, https://github.com/dgarnitz/vectorflow/issues
Author-email: David Garnitz <david@getvectorflow.com>
Classifier: License :: OSI Approved :: MIT License
Classifier: Operating System :: OS Independent
Classifier: Programming Language :: Python :: 3
Requires-Python: >=3.9
Requires-Dist: openai~=1.3.6
Requires-Dist: posthog~=3.0.2
Requires-Dist: requests~=2.31.0
Requires-Dist: tiktoken~=0.5.1
